minio/__init__.py
minio/minio_module.py
minio/minio_provider.py
minio/minio_service.py
ascender_minio-0.0.1.dist-info/METADATA
ascender_minio-0.0.1.dist-info/WHEEL
ascender_minio-0.0.1.dist-info/RECORD
