Metadata-Version: 2.1
Name: ascender-minio
Version: 0.0.1
Summary: A simple s3 storage service SDK tailored for Ascender Framework and it's DI.
Author: AgentHub Community
Requires-Python: >=3.11,<3.14
Classifier: Programming Language :: Python :: 3
Classifier: Programming Language :: Python :: 3.11
Classifier: Programming Language :: Python :: 3.12
Requires-Dist: aiobotocore (>=2.21.1,<3.0.0)
Requires-Dist: ascender-framework (>=2.0rc2,<3.0)
Requires-Dist: types-aiobotocore-s3 (>=2.21.1,<3.0.0)
